tcr_roboclaw/__init__.py
tcr_roboclaw/roboclaw.py
tcr_roboclaw-0.1.2.dist-info/WHEEL
tcr_roboclaw-0.1.2.dist-info/METADATA
tcr_roboclaw-0.1.2.dist-info/RECORD
