Metadata-Version: 2.1
Name: tcr-roboclaw
Version: 0.1.2
Summary: An easy to install version of Basicmicro's RoboClaw Python library
Author-email: damienlarocque <phicoltan@gmail.com>
Classifier: Development Status :: 5 - Production/Stable
Classifier: Intended Audience :: Science/Research
Classifier: Operating System :: OS Independent
Classifier: Programming Language :: Python
Classifier: Programming Language :: Python :: 3
Classifier: Programming Language :: Python :: 3.8
Classifier: Programming Language :: Python :: 3.9
Classifier: Programming Language :: Python :: 3.10
Classifier: Programming Language :: Python :: 3.11
Requires-Dist: pyserial
Requires-Dist: black ; extra == "dev"
Requires-Dist: pylint ; extra == "dev"
Requires-Dist: bump2version ; extra == "dev"
Project-URL: Homepage, https://gitlab.com/team-chat-robotique/libraries/team-chat-robotique-roboclaw-python
Project-URL: Repository on GitLab, https://gitlab.com/team-chat-robotique/libraries/team-chat-robotique-roboclaw-python
Provides-Extra: dev
